Metadata-Version: 2.1
Name: pyusbdux
Version: 2.0.4
Summary: API for the USB-DUX DAQ boxes for Linux (https://github.com/glasgowneuro/usbdux)
Home-page: https://github.com/glasgowneuro/usbdux
Author: Bernd Porr
Author-email: mail@berndporr.me.uk
License: GPL v3
Platform: UNKNOWN
Classifier: Intended Audience :: Developers
Classifier: Operating System :: POSIX
Classifier: Programming Language :: Python :: 3
License-File: LICENSE
